git_bt_backup_tools/__init__.py
git_bt_backup_tools/configure_git.py
git_bt_backup_tools/pretty_print.py
git_bt_backup_tools-0.2.0.9008.dist-info/entry_points.txt
git_bt_backup_tools-0.2.0.9008.dist-info/LICENSE
git_bt_backup_tools-0.2.0.9008.dist-info/WHEEL
git_bt_backup_tools-0.2.0.9008.dist-info/METADATA
git_bt_backup_tools-0.2.0.9008.dist-info/RECORD
