Metadata-Version: 2.1
Name: git-bt-backup-tools
Version: 0.2.0.9008
Summary: 
Author: Smitten
Author-email: 77771103+C84186@users.noreply.github.com
Requires-Python: >=3.8,<4.0
Classifier: Programming Language :: Python :: 3
Classifier: Programming Language :: Python :: 3.8
Classifier: Programming Language :: Python :: 3.9
Requires-Dist: PyYAML (>=5.4.1,<6.0.0)
Requires-Dist: bencode.py (>=4.0.0,<5.0.0)
Requires-Dist: click (>=7.1.2,<8.0.0)
